dygest/__init__.py
dygest/cli.py
dygest/config.py
dygest/core.py
dygest/json_schemas.py
dygest/llms.py
dygest/ner_utils.py
dygest/output_utils.py
dygest/prompts.py
dygest/translations.py
dygest/utils.py
dygest/templates/plain/plain.css
dygest/templates/plain/plain.html
dygest/templates/tabs/tabs.css
dygest/templates/tabs/tabs.html
dygest/templates/tabs/tabs.js
dygest-0.7.0.dist-info/licenses/LICENSE
dygest-0.7.0.dist-info/METADATA
dygest-0.7.0.dist-info/WHEEL
dygest-0.7.0.dist-info/entry_points.txt
dygest-0.7.0.dist-info/top_level.txt
dygest-0.7.0.dist-info/RECORD
