Metadata-Version: 2.4
Name: dygest
Version: 0.7.0
Summary: DYGEST: Document Insights Generator
Home-page: https://github.com/tsmdt/dygest
Author: Thomas Schmidt
License: MIT
Project-URL: Homepage, https://github.com/tsmdt/dygest
Classifier: Programming Language :: Python :: 3
Classifier: License :: OSI Approved :: MIT License
Classifier: Operating System :: OS Independent
Requires-Python: >=3.10
License-File: LICENSE
Requires-Dist: click==8.3.0
Requires-Dist: typer==0.19.2
Requires-Dist: tiktoken==0.11.0
Requires-Dist: beautifulsoup4==4.13.5
Requires-Dist: flair==0.15.1
Requires-Dist: tqdm==4.67.1
Requires-Dist: langdetect==1.0.9
Requires-Dist: json_repair==0.51.0
Requires-Dist: litellm==1.77.4
Requires-Dist: markitdown==0.1.3
Dynamic: license-file
